featman/__init__.py
featman/main.py
featman/tracker.py
featman-0.1.5.dist-info/METADATA
featman-0.1.5.dist-info/WHEEL
featman-0.1.5.dist-info/top_level.txt
featman-0.1.5.dist-info/RECORD
