Metadata-Version: 2.1
Name: featman
Version: 0.1.5
Summary: A built up feature tool. Used to make everything simipler
Home-page: UNKNOWN
Author: Kevin Hill
Author-email: kevin@funguana.com
License: UNKNOWN
Platform: UNKNOWN
Classifier: Programming Language :: Python :: 3
Classifier: License :: OSI Approved :: MIT License
Classifier: Operating System :: OS Independent
Requires-Dist: crayons
Requires-Dist: spaceman
Requires-Dist: coolname
Requires-Dist: toolz
Requires-Dist: dask
Requires-Dist: pandas
Requires-Dist: maya
Requires-Dist: loguru
